TrimPy/__init__.py
TrimPy/__main__.py
TrimPy/enum/animation.py
TrimPy/enum/mode.py
TrimPy/enum/pattern.py
TrimPy/enum/trim.py
TrimPy/messages/helpers.py
TrimPy/messages/message.py
TrimPy/messages/parser.py
TrimPy-1.1.0.dist-info/LICENSE.md
TrimPy-1.1.0.dist-info/METADATA
TrimPy-1.1.0.dist-info/WHEEL
TrimPy-1.1.0.dist-info/entry_points.txt
TrimPy-1.1.0.dist-info/top_level.txt
TrimPy-1.1.0.dist-info/RECORD
