Metadata-Version: 2.2
Name: TrimPy
Version: 1.1.0
Summary: A basic API implementation for Trimlight Select systems.
Home-page: https://github.com/ecdye/TrimPy
Author: Ethan Dye
Author-email: mrtops03@gmail.com
Project-URL: Bug Tracker, https://github.com/ecdye/TrimPy/issues
Classifier: Programming Language :: Python :: 3.6
Classifier: License :: OSI Approved :: GNU General Public License v3 (GPLv3)
Classifier: Operating System :: OS Independent
Classifier: Development Status :: 5 - Production/Stable
Requires-Python: >=3.6
License-File: LICENSE.md
Dynamic: author
Dynamic: author-email
Dynamic: classifier
Dynamic: description
Dynamic: description-content-type
Dynamic: home-page
Dynamic: project-url
Dynamic: requires-python
Dynamic: summary
